gitscribe/__init__.py
gitscribe/__main__.py
gitscribe/cli.py
gitscribe/config.py
gitscribe/git_integration.py
gitscribe/parsers.py
gitscribe/rag.py
gitscribe/scraper.py
gitscribe/server.py
gitscribe/utils.py
gitscribe_mcp-1.1.5.dist-info/METADATA
gitscribe_mcp-1.1.5.dist-info/WHEEL
gitscribe_mcp-1.1.5.dist-info/entry_points.txt
gitscribe_mcp-1.1.5.dist-info/RECORD
