Metadata-Version: 2.4
Name: gitscribe-mcp
Version: 1.1.5
Summary: GitScribe: Web Scraping RAG MCP Server for Git-based Documentation
Project-URL: Homepage, https://github.com/akhilthomas236/gitscribe
Project-URL: Bug Reports, https://github.com/akhilthomas236/gitscribe/issues
Project-URL: Source, https://github.com/akhilthomas236/gitscribe
Project-URL: PyPI, https://pypi.org/project/gitscribe-mcp/
Author-email: GitScribe Team <contact@gitscribe.dev>
Keywords: documentation,git,mcp,rag,retrieval,scraping,search
Classifier: Development Status :: 4 - Beta
Classifier: Intended Audience :: Developers
Classifier: License :: OSI Approved :: MIT License
Classifier: Programming Language :: Python :: 3
Classifier: Programming Language :: Python :: 3.10
Classifier: Programming Language :: Python :: 3.11
Classifier: Programming Language :: Python :: 3.12
Classifier: Topic :: Internet :: WWW/HTTP :: Indexing/Search
Classifier: Topic :: Software Development :: Documentation
Classifier: Topic :: Text Processing :: Indexing
Requires-Python: >=3.10
Requires-Dist: aiofiles>=24.1.0
Requires-Dist: aiohttp>=3.9.0
Requires-Dist: beautifulsoup4>=4.12.0
Requires-Dist: chromadb>=0.4.15
Requires-Dist: gitpython>=3.1.40
Requires-Dist: html2text>=2020.1.16
Requires-Dist: markdown>=3.5.0
Requires-Dist: mcp>=0.1.0
Requires-Dist: numpy>=1.24.0
Requires-Dist: python-dotenv>=1.0.0
Requires-Dist: pyyaml>=6.0.1
Requires-Dist: requests>=2.31.0
Requires-Dist: sentence-transformers>=2.2.2
Provides-Extra: dev
Requires-Dist: black>=23.0.0; extra == 'dev'
Requires-Dist: chardet>=5.2.0; extra == 'dev'
Requires-Dist: flake8>=6.0.0; extra == 'dev'
Requires-Dist: mypy>=1.5.0; extra == 'dev'
Requires-Dist: pytest-asyncio>=0.21.0; extra == 'dev'
Requires-Dist: pytest>=7.4.0; extra == 'dev'
Requires-Dist: python-magic>=0.4.27; extra == 'dev'
